LICENSE
MANIFEST.in
README.md
requirements.txt
setup.py
slackipycore/__init__.py
slackipycore/main.py
slackipycore/slackipy_exceptions.py
slackipycore.egg-info/PKG-INFO
slackipycore.egg-info/SOURCES.txt
slackipycore.egg-info/dependency_links.txt
slackipycore.egg-info/requires.txt
slackipycore.egg-info/top_level.txt